{
  "meta": {
    "preset": "SMUGGLER",
    "gender": "male",
    "maxTurns": 30,
    "actualTurns": 1,
    "timestamp": "2026-04-01 10:50:04",
    "git": {
      "hash": "0fc3778",
      "branch": "main",
      "message": "feat: 퀘스트 Fact 매칭 개선 — shouldMatchEvent 확장(D) + weight 부스트(A) + NPC ID 정규화"
    }
  },
  "runId": "571bfb30-08a0-4d53-9d8e-ddc113271639",
  "turns": [
    {
      "turn": 1,
      "turnNo": 0,
      "nodeType": "HUB",
      "input": "CHOICE:accept_quest",
      "hp": 80,
      "eventId": "",
      "resolveOutcome": null,
      "nodeOutcome": "ONGOING",
      "events": [
        "SYSTEM"
      ],
      "narrative": "서술을 불러오지 못했습니다."
    }
  ],
  "finalState": {
    "hp": null,
    "gold": null,
    "npcStates": {},
    "worldState": {
      "hubHeat": null,
      "activeIncidents": [],
      "day": null,
      "globalClock": null
    },
    "memory": {},
    "discoveredQuestFacts": []
  },
  "verification": {
    "V1_incidents": false,
    "V2_encounter": false,
    "V3_posture": true,
    "V4_emotion": false,
    "V5_memory": false,
    "V6_resolve": false
  },
  "narrativeMetrics": {
    "totalNarratives": 1,
    "totalChars": 15,
    "avgCharsPerTurn": 15.0,
    "minChars": 15,
    "maxChars": 15,
    "totalDialogues": 0,
    "haoSoRatio": 0,
    "metaExpressionCount": 0,
    "speechContamination": 0,
    "exitKeywordCount": 0,
    "reapproachCount": 0
  },
  "outcomeDistribution": {
    "success": 0,
    "partial": 0,
    "fail": 0,
    "total": 0
  }
}